pymailai/__init__.py
pymailai/agent.py
pymailai/base_client.py
pymailai/client.py
pymailai/config.py
pymailai/email_processor.py
pymailai/email_reply.py
pymailai/email_validator.py
pymailai/gmail.py
pymailai/gmail_client.py
pymailai/html_converter.py
pymailai/markdown_converter.py
pymailai/message.py
pymailai/text_processor.py
pymailai/tools/__init__.py
pymailai/tools/core.py
pymailai/tools/schemas.py
pymailai-0.1.6.dist-info/METADATA
pymailai-0.1.6.dist-info/WHEEL
pymailai-0.1.6.dist-info/licenses/LICENSE
pymailai-0.1.6.dist-info/RECORD
