Metadata-Version: 2.4
Name: pymailai
Version: 0.1.6
Summary: Email interface for AI agents
Author: Ivan Iufriakov
License-Expression: MIT
License-File: LICENSE
Classifier: License :: OSI Approved :: MIT License
Classifier: Operating System :: OS Independent
Classifier: Programming Language :: Python :: 3
Requires-Python: >=3.12
Requires-Dist: aioimaplib>=1.0.1
Requires-Dist: aiosmtplib>=2.0.2
Requires-Dist: beautifulsoup4>=4.12.0
Requires-Dist: email-validator>=2.0.0
Requires-Dist: google-api-python-client>=2.95.0
Requires-Dist: google-auth-oauthlib>=1.0.0
Requires-Dist: google-auth>=2.22.0
Requires-Dist: markdown>=3.4.0
Requires-Dist: python-dotenv>=1.0.0
Provides-Extra: all
Requires-Dist: anthropic>=0.3.0; extra == 'all'
Requires-Dist: ollama>=0.4.4; extra == 'all'
Requires-Dist: openai>=1.0.0; extra == 'all'
Requires-Dist: pydantic>=2.0.0; extra == 'all'
Provides-Extra: anthropic
Requires-Dist: anthropic>=0.3.0; extra == 'anthropic'
Provides-Extra: dev
Requires-Dist: black>=23.0.0; extra == 'dev'
Requires-Dist: flake8>=6.1.0; extra == 'dev'
Requires-Dist: isort>=5.0.0; extra == 'dev'
Requires-Dist: mypy>=1.0.0; extra == 'dev'
Requires-Dist: pytest-asyncio>=0.23.0; extra == 'dev'
Requires-Dist: pytest-cov>=4.1.0; extra == 'dev'
Requires-Dist: pytest-mock>=3.10.0; extra == 'dev'
Requires-Dist: pytest>=7.0.0; extra == 'dev'
Provides-Extra: ollama
Requires-Dist: ollama>=0.4.4; extra == 'ollama'
Provides-Extra: openai
Requires-Dist: openai>=1.0.0; extra == 'openai'
Requires-Dist: pydantic>=2.0.0; extra == 'openai'
